azure_monitor/__init__.py
azure_monitor/protocol.py
azure_monitor/trace.py
azure_monitor/util.py
azure_monitor/version.py
opentelemetry_azure_monitor_exporter-0.1a2.dist-info/METADATA
opentelemetry_azure_monitor_exporter-0.1a2.dist-info/WHEEL
opentelemetry_azure_monitor_exporter-0.1a2.dist-info/top_level.txt
opentelemetry_azure_monitor_exporter-0.1a2.dist-info/RECORD
